{
  "metro": "Austin–Round Rock–Georgetown",
  "city": "Austin",
  "state": "TX",
  "count": 3,
  "averageScore": "20.0",
  "highPerformerShare": 0,
  "narrative": "Overall, Austin shows a smaller share of top performers. The average SunsetWell score suggests mixed quality across the market. Families should still compare options on inspection history, staffing hours, and care stability.",
  "table": [
    {
      "rank": 1,
      "facilityId": "455599",
      "title": "HERITAGE PARK REHABILITATION AND SKILLED NURSING C",
      "score": 29,
      "percentile": 29,
      "health": 1,
      "staffing": 3,
      "quality": 5,
      "rnHours": null,
      "totalNurseHours": null
    },
    {
      "rank": 2,
      "facilityId": "676308",
      "title": "SAN GABRIEL REHABILITATION AND CARE CENTER",
      "score": 24,
      "percentile": 24,
      "health": 2,
      "staffing": 1,
      "quality": 3,
      "rnHours": null,
      "totalNurseHours": null
    },
    {
      "rank": 3,
      "facilityId": "455862",
      "title": "CORAL REHABILITATION AND NURSING OF AUSTIN",
      "score": 7,
      "percentile": 7,
      "health": 1,
      "staffing": 1,
      "quality": 5,
      "rnHours": null,
      "totalNurseHours": null
    }
  ]
}